Metadata-Version: 2.1
Name: fodMC
Version: 1.1.0
Summary: Fermi-orbital descriptor Monte-Carlo
Home-page: https://gitlab.com/opensic/fodMC
Author: Kai Trepte
Author-email: kai.trepte1987@gmail.com
License: APACHE2.0
Platform: UNKNOWN
License-File: LICENSE
